witchie/__init__.py
witchie/__main__.py
witchie/api.py
witchie/auth.py
witchie/cache.py
witchie/commands.py
witchie/config.py
witchie/console.py
witchie/entities.py
witchie/exceptions.py
witchie/http.py
witchie/logging.py
witchie/output.py
witchie/settings.py
witchie/typing_compat.py
witchie/wcstring.py
witchie/tui/NOTES.md
witchie/tui/__init__.py
witchie/tui/app.py
witchie/tui/compose.py
witchie/tui/constants.py
witchie/tui/entities.py
witchie/tui/overlays.py
witchie/tui/poll.py
witchie/tui/scroll.py
witchie/tui/timeline.py
witchie/tui/utils.py
witchie/tui/widgets.py
witchie/tui/richtext/__init__.py
witchie/tui/richtext/richtext.py
witchie/utils/__init__.py
witchie/utils/datetime.py
witchie/utils/language.py
witchie-0.40.0.dist-info/entry_points.txt
witchie-0.40.0.dist-info/LICENSE
witchie-0.40.0.dist-info/WHEEL
witchie-0.40.0.dist-info/METADATA
witchie-0.40.0.dist-info/RECORD
