Metadata-Version: 2.1
Name: witchie
Version: 0.40.0
Summary: Akkoma CLI client
Author-email: Ngô Ngọc Đức Huy <huyngo@disroot.org>, Ivan Habunek <ivan@habunek.com>
Maintainer-email: Ngô Ngọc Đức Huy <huyngo@disroot.org>
Requires-Python: >=3.9
Classifier: Development Status :: 4 - Beta
Classifier: Environment :: Console :: Curses
Classifier: Environment :: Console
Classifier: License :: OSI Approved :: GNU General Public License v3 (GPLv3)
Classifier: Programming Language :: Python :: 3
Requires-Dist: requests>=2.13,<3.0
Requires-Dist: wcwidth>=0.1.7
Requires-Dist: tomlkit>=0.10.0,<1.0
Requires-Dist: coverage ; extra == "dev"
Requires-Dist: pyyaml ; extra == "dev"
Requires-Dist: twine ; extra == "dev"
Requires-Dist: wheel ; extra == "dev"
Requires-Dist: urwidgets>=0.1,<0.2 ; extra == "richtext"
Requires-Dist: flake8 ; extra == "test"
Requires-Dist: pytest ; extra == "test"
Requires-Dist: vermin ; extra == "test"
Requires-Dist: beautifulsoup4>=4.5.0,<5.0 ; extra == "tui"
Requires-Dist: urwid>=2.0.0,<3.0 ; extra == "tui"
Project-URL: Documentation, https://man.sr.ht/~huyngo/witchie
Project-URL: Home, https://sr.ht/~huyngo/witchie
Project-URL: Issue tracker, https://todo.sr.ht/~huyngo/witchie
Project-URL: Source, https://git.sr.ht/~huyngo/witchie
Provides-Extra: dev
Provides-Extra: richtext
Provides-Extra: test
Provides-Extra: tui
